cryosparc_tools-4.7.1.dist-info/RECORD
cryosparc_tools-4.7.1.dist-info/WHEEL
cryosparc_tools-4.7.1.dist-info/top_level.txt
cryosparc_tools-4.7.1.dist-info/METADATA
cryosparc_tools-4.7.1.dist-info/licenses/LICENSE
cryosparc_tools-4.7.1.data/headers/dataset.h
cryosparc/dataset.c
cryosparc/command.py
cryosparc/core.cpython-313-darwin.so
cryosparc/lz4.pxd
cryosparc/util.py
cryosparc/dtype.py
cryosparc/job.py
cryosparc/tools.py
cryosparc/constants.py
cryosparc/star.py
cryosparc/__init__.py
cryosparc/spec.py
cryosparc/stream.py
cryosparc/core.c
cryosparc/dataset.py
cryosparc/mrc.py
cryosparc/errors.py
cryosparc/workspace.py
cryosparc/core.pyx
cryosparc/row.py
cryosparc/project.py
cryosparc/column.py
cryosparc/dataset.pxd
cryosparc/include/lz4/lib/LICENSE
cryosparc/include/lz4/lib/lz4.h
cryosparc/include/lz4/lib/lz4.c
cryosparc/include/cryosparc-tools/dataset.h
