Metadata-Version: 2.1
Name: cryosparc-tools
Version: 4.7.1
Summary: Toolkit for interfacing with CryoSPARC
Author-email: "Structura Biotechnology Inc." <info@structura.bio>
License: Copyright 2025 Structura Biotechnology Inc.
Project-URL: Homepage, https://tools.cryosparc.com
Project-URL: Documentation, https://tools.cryosparc.com
Project-URL: Repository, https://github.com/cryoem-uoft/cryosparc-tools
Project-URL: Changelog, https://github.com/cryoem-uoft/cryosparc-tools/blob/main/CHANGELOG.md
Classifier: Development Status :: 5 - Production/Stable
Classifier: Operating System :: MacOS
Classifier: Operating System :: Microsoft :: Windows
Classifier: Operating System :: POSIX :: Linux
Classifier: Programming Language :: C
Classifier: Programming Language :: Python
Classifier: Topic :: Scientific/Engineering
Classifier: Topic :: Software Development :: Libraries :: Python Modules
Classifier: Topic :: Software Development :: Libraries
Requires-Python: >=3.7
License-File: LICENSE
Requires-Dist: numpy <3.0,>=1.15
Requires-Dist: typing-extensions >=3.7
Provides-Extra: build
Requires-Dist: build ; extra == 'build'
Requires-Dist: autodocsumm ; extra == 'build'
Requires-Dist: cython ; extra == 'build'
Requires-Dist: jupyter-book ; extra == 'build'
Provides-Extra: dev
Requires-Dist: build ; extra == 'dev'
Requires-Dist: cython ; extra == 'dev'
Requires-Dist: httpretty ; extra == 'dev'
Requires-Dist: pre-commit ; extra == 'dev'
Requires-Dist: pyright ; extra == 'dev'
Requires-Dist: pytest-benchmark ; extra == 'dev'
Requires-Dist: pytest-xdist[psutil] ; extra == 'dev'
Requires-Dist: pytest ; extra == 'dev'
Requires-Dist: ruff ; extra == 'dev'
Requires-Dist: setuptools ; extra == 'dev'
